vivaldi_a/__init__.py
vivaldi_a/analysis/Calc_Emis.py
vivaldi_a/analysis/Regridding_ESMF.py
vivaldi_a/analysis/__init__.py
vivaldi_a/plot/Plot_2D.py
vivaldi_a/plot/__init__.py
vivaldi_a-0.2.7.dist-info/METADATA
vivaldi_a-0.2.7.dist-info/WHEEL
vivaldi_a-0.2.7.dist-info/top_level.txt
vivaldi_a-0.2.7.dist-info/RECORD
