Metadata-Version: 2.1
Name: vivaldi-a
Version: 0.2.7
Summary: Visualization Validation and Diagnostics for Atmospheric chemistry
Home-page: https://ncar.github.io/CAM-chem/
Author: Rebecca Buchholz;Duseong Jo
Author-email: cdswk@ucar.edu
License: UNKNOWN
Keywords: atmospheric chemistry,cesm,cam-chem,air quality,emission
Platform: UNKNOWN
Classifier: Programming Language :: Python :: 3.7
Classifier: Topic :: Scientific/Engineering :: Atmospheric Science
Classifier: Topic :: Scientific/Engineering :: Chemistry
Classifier: Topic :: Utilities
Requires-Dist: numpy
Requires-Dist: matplotlib
Requires-Dist: xarray
Requires-Dist: cartopy
Requires-Dist: cftime
Requires-Dist: ESMPy (>=8.1.0)
Requires-Dist: netCDF4
